poetry_semantic_release_test/__init__.py
poetry_semantic_release_test/util.py
poetry_semantic_release_test-0.1.2.dist-info/LICENSE
poetry_semantic_release_test-0.1.2.dist-info/METADATA
poetry_semantic_release_test-0.1.2.dist-info/WHEEL
poetry_semantic_release_test-0.1.2.dist-info/RECORD
